{
	"chargeDeviceID": "1e2184e9a38acddfb65b66905ad70f9a",
	"reference": "GBALLEGO000167",
	"name": "SHELL RECHARGE PLOUGH LANE",
	"latitude": 51.429853,
	"longitude": -0.185911,
	"subBuildingName": null,
	"buildingName": "SHELL PLOUGH LANE",
	"buildingNumber": null,
	"thoroughfare": null,
	"street": "59 Plough Lane",
	"doubleDependantLocality": null,
	"dependantLocality": null,
	"town": "London",
	"county": "London",
	"postcode": "SW17 0BW",
	"countryCode": "gb",
	"uprn": null,
	"deviceDescription": null,
	"locationShortDescription": null,
	"locationLongDescription": null,
	"deviceManufacturer": "Efacec",
	"deviceModel": "QC45",
	"deviceOwnerName": "Shell UK Oil Products Limited",
	"deviceOwnerWebsite": "http://www.shell.co.uk/motorist/welcome-to-shell-recharge.html",
	"deviceOwnerTelephoneNo": "08000294601",
	"deviceOwnerContactName": null,
	"deviceControllerName": "Shell Recharge",
	"deviceControllerWebsite": "http://www.shell.co.uk/motorist/welcome-to-shell-recharge.html",
	"deviceControllerTelephoneNo": "08000294601",
	"deviceControllerContactName": null,
	"deviceNetworks": "Shell Recharge",
	"chargeDeviceStatus": "In service",
	"publishStatus": "Published",
	"deviceValidated": null,
	"dateCreated": "2021-06-15 19:00:55",
	"dateUpdated": "2021-06-15 19:00:55",
	"moderated": "N",
	"lastUpdated": null,
	"lastUpdatedBy": null,
	"attribution": "Shell Recharge",
	"dateDeleted": "n/a",
	"paymentRequired": 1,
	"paymentRequiredDetails": null,
	"subscriptionRequired": null,
	"subscriptionRequiredDetails": null,
	"parkingFeesFlag": null,
	"parkingFeesDetails": null,
	"parkingFeesUrl": null,
	"accessRestrictionFlag": null,
	"accessRestrictionDetails": null,
	"physicalRestrictionFlag": null,
	"physicalRestrictionText": null,
	"onStreetFlag": null,
	"locationType": "Service station",
	"bearing": null,
	"access24Hours": 1,
	"accessMondayFrom": null,
	"accessMondayTo": null,
	"accessTuesdayFrom": null,
	"accessTuesdayTo": null,
	"accessWednesdayFrom": null,
	"accessWednesdayTo": null,
	"accessThursdayFrom": null,
	"accessThursdayTo": null,
	"accessFridayFrom": null,
	"accessFridayTo": null,
	"accessSaturdayFrom": null,
	"accessSaturdayTo": null,
	"accessSundayFrom": null,
	"accessSundayTo": null,
	"connector1ID": 163138,
	"connector1Type": "Type 2 Mennekes (IEC62196)",
	"connector1RatedOutputKW": 43.0,
	"connector1OutputCurrent": 63,
	"connector1RatedVoltage": 400,
	"connector1ChargeMethod": "Three Phase AC",
	"connector1ChargeMode": 3,
	"connector1TetheredCable": 1,
	"connector1Status": "In service",
	"connector1Description": null,
	"connector1Validated": null,
	"connector2ID": 163139,
	"connector2Type": "CCS Type 2 Combo (IEC62196)",
	"connector2RatedOutputKW": 50.0,
	"connector2OutputCurrent": 125,
	"connector2RatedVoltage": 400,
	"connector2ChargeMethod": "DC",
	"connector2ChargeMode": 4,
	"connector2TetheredCable": 1,
	"connector2Status": "In service",
	"connector2Description": null,
	"connector2Validated": null,
	"connector3ID": 163140,
	"connector3Type": "JEVS G105 (CHAdeMO) DC",
	"connector3RatedOutputKW": 50.0,
	"connector3OutputCurrent": 125,
	"connector3RatedVoltage": 400,
	"connector3ChargeMethod": "DC",
	"connector3ChargeMode": 4,
	"connector3TetheredCable": 1,
	"connector3Status": "In service",
	"connector3Description": null,
	"connector3Validated": null,
	"connector4ID": null,
	"connector4Type": null,
	"connector4RatedOutputKW": null,
	"connector4OutputCurrent": null,
	"connector4RatedVoltage": null,
	"connector4ChargeMethod": null,
	"connector4ChargeMode": null,
	"connector4TetheredCable": null,
	"connector4Status": null,
	"connector4Description": null,
	"connector4Validated": null,
	"connector5ID": null,
	"connector5Type": null,
	"connector5RatedOutputKW": null,
	"connector5OutputCurrent": null,
	"connector5RatedVoltage": null,
	"connector5ChargeMethod": null,
	"connector5ChargeMode": null,
	"connector5TetheredCable": null,
	"connector5Status": null,
	"connector5Description": null,
	"connector5Validated": null,
	"connector6ID": null,
	"connector6Type": null,
	"connector6RatedOutputKW": null,
	"connector6OutputCurrent": null,
	"connector6RatedVoltage": null,
	"connector6ChargeMethod": null,
	"connector6ChargeMode": null,
	"connector6TetheredCable": null,
	"connector6Status": null,
	"connector6Description": null,
	"connector6Validated": null,
	"connector7ID": null,
	"connector7Type": null,
	"connector7RatedOutputKW": null,
	"connector7OutputCurrent": null,
	"connector7RatedVoltage": null,
	"connector7ChargeMethod": null,
	"connector7ChargeMode": null,
	"connector7TetheredCable": null,
	"connector7Status": null,
	"connector7Description": null,
	"connector7Validated": null,
	"connector8ID": null,
	"connector8Type": null,
	"connector8RatedOutputKW": null,
	"connector8OutputCurrent": null,
	"connector8RatedVoltage": null,
	"connector8ChargeMethod": null,
	"connector8ChargeMode": null,
	"connector8TetheredCable": null,
	"connector8Status": null,
	"connector8Description": null,
	"connector8Validated": null
}
